cdsclient/LICENSE.txt
cdsclient/__init__.py
cdsclient/find_2020aj_159_84b.py
cdsclient/find_2mass.py
cdsclient/find_2mass6x.py
cdsclient/find_2psc3.py
cdsclient/find_allwise.py
cdsclient/find_allwise.v2.py
cdsclient/find_allwise_v2.py
cdsclient/find_apass9.py
cdsclient/find_apm.py
cdsclient/find_apop.py
cdsclient/find_atlas_refcat2.py
cdsclient/find_attitude.py
cdsclient/find_catwise.py
cdsclient/find_catwise2020.py
cdsclient/find_cfht_ls_d1to4.py
cdsclient/find_cfht_ls_w1to4.py
cdsclient/find_cmc14.py
cdsclient/find_cmc15.py
cdsclient/find_const.py
cdsclient/find_denis3.py
cdsclient/find_des_dr1.py
cdsclient/find_des_dr2.py
cdsclient/find_desi_lis_dr8_pzn.py
cdsclient/find_desi_lis_dr8_pzs.py
cdsclient/find_erass1_simu_agnin.py
cdsclient/find_gaia2_allwise_yso.py
cdsclient/find_gaia2_dist.py
cdsclient/find_gaia_dr1.py
cdsclient/find_gaia_dr2.py
cdsclient/find_gaia_dr2_teff.py
cdsclient/find_gaia_dr3.py
cdsclient/find_gaia_dr3_astroparams.py
cdsclient/find_gaia_dr3_astroparamssupp.py
cdsclient/find_gaia_dr3_epochphot.py
cdsclient/find_gaia_dr3_rvsmean.py
cdsclient/find_gaia_dr3_ssoobs.py
cdsclient/find_gaia_dr3_syntphot.py
cdsclient/find_gaia_dr3_varispursign.py
cdsclient/find_gaia_dr3_varisum.py
cdsclient/find_gaia_dr3_xpcont.py
cdsclient/find_gaia_dr3_xpsum.py
cdsclient/find_gaia_edr3.py
cdsclient/find_gaia_edr3_dist.py
cdsclient/find_gaia_fpr_lensobs.py
cdsclient/find_gaia_fpr_ssoobs.py
cdsclient/find_gaia_gums_gal.py
cdsclient/find_galex_gr5_ais.py
cdsclient/find_galex_gr5_mis.py
cdsclient/find_galex_gr67.py
cdsclient/find_gdr2_wise_gp.py
cdsclient/find_gdr2ap.py
cdsclient/find_glimpse.py
cdsclient/find_gps1.py
cdsclient/find_gps1_plus.py
cdsclient/find_gsc.py
cdsclient/find_gsc1.2.py
cdsclient/find_gsc1.3.py
cdsclient/find_gsc1_2.py
cdsclient/find_gsc1_3.py
cdsclient/find_gsc2.3.py
cdsclient/find_gsc242.py
cdsclient/find_gsc242_v2.py
cdsclient/find_gsc2_3.py
cdsclient/find_gums10_lmc.py
cdsclient/find_gums10_mw.py
cdsclient/find_gums10_smc.py
cdsclient-1.1.9.dist-info/METADATA
cdsclient-1.1.9.dist-info/WHEEL
cdsclient-1.1.9.dist-info/RECORD
