Metadata-Version: 2.3
Name: cdsclient
Version: 1.1.9
Summary: CDS VizieR client (query large table)
Project-URL: repository, https://github.com/cds-astro/cds.cdsclient
Author: Gilles Landais (CDS)
Keywords: astronomy
Classifier: Intended Audience :: Science/Research
Classifier: License :: OSI Approved :: BSD License
Classifier: Operating System :: OS Independent
Classifier: Programming Language :: Python :: 3.6
Classifier: Topic :: Scientific/Engineering :: Astronomy
Requires-Python: >=3.6
Requires-Dist: astropy>=3.2
Requires-Dist: numpy>=1.17.2
